[
    {
        "name": "Muhammad Galhoum",
        "image":"https://media-exp1.licdn.com/dms/image/C4D03AQGevf_OomFDLg/profile-displayphoto-shrink_800_800/0/1653220892966?e=1658966400&v=beta&t=O3up3OfIk760hBlTaxO0aybibj1bU-3bvCYZfVVlo24",
        "college": "Faculty of Science Menofia university",
        "twitter":"https://twitter.com/muhammadgalhoum",
        "linkedin": "https://www.linkedin.com/in/muhammadgalhoum/",
        "github": "https://github.com/muhammadgalhoum"
        

    },
    {
        "name": "Nikhil Raj",
        "image":"https://avatars.githubusercontent.com/u/93156825?v=4",
        "college": "Heritage Institute of Technology",
        "twitter":"https://twitter.com/humans_write",
        "linkedin": "https://www.linkedin.com/in/nikhil-raj-117246232/",
        "github": "https://github.com/nikhil25803"
        

    },
    {
        "name": "Utkarsh Rai",
        "image":"https://avatars.githubusercontent.com/u/95978839?v=4",
        "college": "USICT",
        "twitter":"#",
        "linkedin": "https://www.linkedin.com/in/utkarsh-rai-943777224/",
        "github": "https://github.com/Ultimateutkarsh11"
        

    },
    {
        "name": "Shreya",
        "image":"https://avatars.githubusercontent.com/u/63296631?v=4",
        "college": "Amity University",
        "twitter":"#",
        "linkedin": "http://linkedin.com/in/miss-shreya-8209a2190",
        "github": "https://github.com/Shreya-spec"
        

    },
    {
        "name": "Vaibhav Srivastava",
        "image":"https://avatars.githubusercontent.com/u/86517958?v=4",
        "college": "Madan Mohan Malviya University of Technology",
        "twitter":"https://twitter.com/Vaibhav28779078",
        "linkedin": "https://www.linkedin.com/in/vaibhav-srivastava-bb0998202/",
        "github": "https://github.com/myhacktech"
        

    },
    {
        "name": "Jayanth MKV",
        "image":"https://avatars.githubusercontent.com/u/93820457?v=4",
        "college": "JNTU-GV",
        "twitter":"https://twitter.com/JayanthMarina",
        "linkedin": "#",
        "github": "https://github.com/Jayanth-MKV"
        

    }
]